ai2thor_colab/__init__.py
ai2thor_colab-0.1.2.dist-info/LICENSE
ai2thor_colab-0.1.2.dist-info/METADATA
ai2thor_colab-0.1.2.dist-info/WHEEL
ai2thor_colab-0.1.2.dist-info/top_level.txt
ai2thor_colab-0.1.2.dist-info/RECORD
