Metadata-Version: 2.1
Name: ai2thor-colab
Version: 0.1.2
Summary: Utility functions for using AI2-THOR with Google Colab.
Home-page: https://github.com/allenai/ai2thor-colab
Author: Allen Institute for AI
Author-email: ai2thor@allenai.org
License: Apache 2.0
Platform: UNKNOWN
Classifier: Intended Audience :: Science/Research
Classifier: Development Status :: 5 - Production/Stable
Classifier: License :: OSI Approved :: Apache Software License
Classifier: Topic :: Scientific/Engineering :: Artificial Intelligence
Classifier: Programming Language :: Python
Classifier: Programming Language :: Python :: 3.6
Classifier: Programming Language :: Python :: 3.7
Classifier: Programming Language :: Python :: 3.8
Classifier: Programming Language :: Python :: 3.9
Requires-Dist: numpy
Requires-Dist: moviepy (>=1.0.3)
Requires-Dist: pandas
Requires-Dist: ai2thor
Requires-Dist: Pillow
